flake8_rst_docstrings-stubs/METADATA.toml
flake8_rst_docstrings-stubs/__init__.pyi
flake8_rst_docstrings-stubs/py.typed
types_flake8_rst_docstrings-0.3.0.20250425.dist-info/licenses/LICENSE
types_flake8_rst_docstrings-0.3.0.20250425.dist-info/METADATA
types_flake8_rst_docstrings-0.3.0.20250425.dist-info/WHEEL
types_flake8_rst_docstrings-0.3.0.20250425.dist-info/top_level.txt
types_flake8_rst_docstrings-0.3.0.20250425.dist-info/RECORD
